flake8_timeout.py
flake8_timeout-2.0.0.dist-info/licenses/LICENCE
flake8_timeout-2.0.0.dist-info/METADATA
flake8_timeout-2.0.0.dist-info/WHEEL
flake8_timeout-2.0.0.dist-info/entry_points.txt
flake8_timeout-2.0.0.dist-info/top_level.txt
flake8_timeout-2.0.0.dist-info/RECORD
