Metadata-Version: 2.4
Name: flake8_timeout
Version: 2.0.0
Summary: flake8 plugin that checks for missing `timeout` parameters in network calls.
Home-page: https://github.com/jkittner/flake8-timeout
Author: Jonas Kittner
Author-email: jkittner@users.noreply.github.com
License: MIT
Classifier: Programming Language :: Python :: 3
Classifier: Programming Language :: Python :: 3 :: Only
Classifier: Programming Language :: Python :: Implementation :: CPython
Requires-Python: >=3.10
License-File: LICENCE
Requires-Dist: flake8
Dynamic: license-file
